CHANGES.rst
LICENSE
MANIFEST.in
README.rst
flask_xuacompatible.py
setup.py
test_xuacompatible.py
flask_xuacompatible.egg-info/PKG-INFO
flask_xuacompatible.egg-info/SOURCES.txt
flask_xuacompatible.egg-info/dependency_links.txt
flask_xuacompatible.egg-info/not-zip-safe
flask_xuacompatible.egg-info/requires.txt
flask_xuacompatible.egg-info/top_level.txt